psu_progs/__init__.py
psu_progs/charge_lithium_ion.py
psu_progs/koradserial.py
psu_progs-0.1.1.dist-info/entry_points.txt
psu_progs-0.1.1.dist-info/WHEEL
psu_progs-0.1.1.dist-info/METADATA
psu_progs-0.1.1.dist-info/RECORD
