Metadata-Version: 2.1
Name: psu-progs
Version: 0.1.1
Summary: CLI tools for Korad power supplies, including lithium ion battery charging
Home-page: https://github.com/theY4Kman/psu-progs
License: MIT
Author: Zach "theY4Kman" Kanzler
Author-email: they4kman@gmail.com
Requires-Python: >=3.9,<4.0
Classifier: License :: OSI Approved :: MIT License
Classifier: Programming Language :: Python :: 3
Classifier: Programming Language :: Python :: 3.9
Classifier: Programming Language :: Python :: 3.10
Classifier: Programming Language :: Python :: 3.11
Requires-Dist: click (>=8.1.3,<9.0.0)
Requires-Dist: pyserial (>=3.5,<4.0)
Project-URL: Repository, https://github.com/theY4Kman/psu-progs
